pydevman/__init__.py
pydevman/__main__.py
pydevman/args.py
pydevman/echo.py
pydevman/log.py
pydevman/algo/__init__.py
pydevman/algo/linklist.py
pydevman/algo/lru.py
pydevman/algo/sort.py
pydevman/algo/tree.py
pydevman/algo/unionfind.py
pydevman/common/result.py
pydevman/common/sorted_key_dict.py
pydevman/config/core.py
pydevman/csv/core.py
pydevman/db/core.py
pydevman/db/mixin.py
pydevman/file/__init__.py
pydevman/file/__main__.py
pydevman/file/common.py
pydevman/file/copy.py
pydevman/file/delete.py
pydevman/file/iter.py
pydevman/file/load.py
pydevman/file/move.py
pydevman/file/stat.py
pydevman/game/__init__.py
pydevman/game/sudoku.py
pydevman/helper/interactive.py
pydevman/helper/merge.py
pydevman/helper/table.py
pydevman/json/__init__.py
pydevman/json/__main__.py
pydevman/json/api.py
pydevman/json/core.py
pydevman/json/inline.py
pydevman/project/scaffold.py
pydevman/query/cache.py
pydevman/query/query.py
pydevman/string/match.py
pydevman/string/rule.py
pydevman/time/core.py
pydevman-0.1.6.dist-info/METADATA
pydevman-0.1.6.dist-info/WHEEL
pydevman-0.1.6.dist-info/entry_points.txt
pydevman-0.1.6.dist-info/top_level.txt
pydevman-0.1.6.dist-info/RECORD
