Metadata-Version: 2.4
Name: pydevman
Version: 0.1.6
Summary: Add your description here
Requires-Python: >=3.9
Requires-Dist: beautifulsoup4>=4.14.2
Requires-Dist: inquirer>=3.4.0
Requires-Dist: omegaconf>=2.3.0
Requires-Dist: pydantic>=2.12.5
Requires-Dist: pyperclip>=1.11.0
Requires-Dist: requests>=2.32.5
Requires-Dist: send2trash>=1.8.3
Requires-Dist: sqlalchemy>=2.0.44
Requires-Dist: tinydb>=4.8.2
Requires-Dist: tomli>=2.3.0
Requires-Dist: typer>=0.20.0
